{
    "ancestors": [
        {
            "external_identifiers": [
                {
                    "identifier": "/repositories/2/archival_objects/77",
                    "source": "archivesspace"
                }
            ],
            "identifier": "5dxgr6z877qq3x46uc9rbcwe35",
            "level": "file",
            "order": null,
            "title": "Meetings",
            "type": "collection"
        },
        {
            "external_identifiers": [
                {
                    "identifier": "/repositories/2/archival_objects/2",
                    "source": "archivesspace"
                }
            ],
            "identifier": "n4z5jafejmf3zbuvydxz76iz95",
            "level": "series",
            "order": null,
            "title": "Laboratory Administration",
            "type": "collection"
        },
        {
            "external_identifiers": [
                {
                    "identifier": "/repositories/2/resources/1",
                    "source": "archivesspace"
                }
            ],
            "identifier": "z96u8h8tuefmbjixtxjta2iun5",
            "level": "collection",
            "order": null,
            "title": "Max Bergmann papers, Rockefeller Institute for Medical Research Scientific Staff",
            "type": "collection"
        }
    ],
    "category": "collections",
    "dates": [
        {
            "begin": "1941",
            "end": "1944",
            "expression": "1941-1944",
            "label": "creation",
            "source": "archivesspace",
            "type": "inclusive"
        }
    ],
    "extents": [
        {
            "type": "folder",
            "value": "1"
        }
    ],
    "external_identifiers": [
        {
            "identifier": "/repositories/2/archival_objects/161",
            "source": "archivesspace"
        }
    ],
    "families": [],
    "formats": [
        "documents"
    ],
    "group": "/collections/z96u8h8tuefmbjixtxjta2iun5",
    "languages": [
        {
            "expression": "English",
            "identifier": "eng"
        }
    ],
    "notes": [],
    "online": false,
    "organizations": [],
    "people": [],
    "rights": [],
    "terms": [],
    "title": "Invitations",
    "tree_position": 0,
    "type": "object",
    "uri": "/objects/3a5o4wyd6d4k7vxmi2mwkpofb3"
}