{
  "dates": [
    {
      "expression": "Aug 20th, 1949 - Sep 24th, 1988", 
      "begin": "1949-08-20", 
      "label": "publication", 
      "end": "1988-09-24", 
      "type": "bulk"
    }, 
    {
      "expression": "Feb 6th, 1914 - May 25th, 2002", 
      "begin": "1914-02-06", 
      "label": "existence", 
      "end": "2002-05-25", 
      "type": "inclusive"
    }
  ], 
  "ancestors": [], 
  "extents": [
    {
      "type": "terabytes", 
      "value": 2
    }
  ], 
  "title": "Voluptate et pariatur amet cillum consectetur duis et cupidatat consequat ex esse sit ullamco.", 
  "notes": [
    {
      "source": "wikidata", 
      "type": "appraisal", 
      "subnotes": [
        {
          "content": [
            "voluptate irure aute duis anim sit", 
            "nulla eu dolore in proident aliqua"
          ], 
          "type": "definedlist"
        }, 
        {
          "content": [
            "elit veniam sit aute commodo minim", 
            "occaecat ea amet culpa minim adipisicing"
          ], 
          "type": "text"
        }, 
        {
          "content": [
            "est dolor ea excepteur esse tempor", 
            "nisi duis officia sunt officia magna", 
            "nostrud ad elit cillum non proident", 
            "proident sunt pariatur ullamco eiusmod nisi"
          ], 
          "type": "orderedlist"
        }
      ], 
      "title": "ea anim elit"
    }, 
    {
      "source": "wikidata", 
      "type": "altformavail", 
      "subnotes": [
        {
          "content": [
            "proident velit exercitation commodo pariatur dolor", 
            "aliquip non irure ullamco culpa laborum"
          ], 
          "type": "orderedlist"
        }
      ], 
      "title": "nulla et cillum"
    }, 
    {
      "source": "archivesspace", 
      "type": "restrictions", 
      "subnotes": [
        {
          "content": [
            "duis est voluptate sit consequat eu", 
            "ut id ea proident deserunt commodo", 
            "occaecat non laborum mollit ad dolore"
          ], 
          "type": "orderedlist"
        }, 
        {
          "content": [
            "fugiat sunt qui incididunt irure qui", 
            "exercitation pariatur officia exercitation deserunt incididunt", 
            "duis proident sit et adipisicing officia", 
            "ex occaecat enim eu aliquip nulla"
          ], 
          "type": "definedlist"
        }
      ], 
      "title": "commodo eu proident"
    }, 
    {
      "source": "archivesspace", 
      "type": "edition", 
      "subnotes": [
        {
          "content": [
            "enim adipisicing laborum aliqua ullamco culpa"
          ], 
          "type": "definedlist"
        }, 
        {
          "content": [
            "tempor irure et aute ut aute"
          ], 
          "type": "definedlist"
        }, 
        {
          "content": [
            "consectetur proident excepteur voluptate irure deserunt"
          ], 
          "type": "orderedlist"
        }
      ], 
      "title": "occaecat esse voluptate"
    }
  ], 
  "external_identifiers": [
    {
      "source": "archivesspace", 
      "identifier": "5d604ab816c0e37fe72f5c30"
    }, 
    {
      "source": "archivesspace", 
      "identifier": "5d604ab826bad253253c6b90"
    }
  ], 
  "languages": [
    {
      "identifier": "spa", 
      "expression": "Spanish"
    }
  ], 
  "rights_statements": [
    {
      "begin": "2019-08-23", 
      "end": "2019-08-23", 
      "copyright_status": "public domain", 
      "notes": [], 
      "jurisdiction": "FR", 
      "other_basis": "sunt", 
      "rights_granted": [
        {
          "restriction": "allow", 
          "begin": "2019-08-23", 
          "end": "2019-08-23", 
          "notes": [], 
          "act": "migrate"
        }
      ], 
      "rights_status": "copyrighted", 
      "determination_date": "2019-08-23", 
      "type": "rights_statement", 
      "id": "5d604ab8ed9dbe311876eafe", 
      "rights_type": "statute"
    }, 
    {
      "begin": "2019-08-23", 
      "end": "2019-08-23", 
      "copyright_status": "copyrighted", 
      "notes": [], 
      "jurisdiction": "US", 
      "other_basis": "sint", 
      "rights_granted": [
        {
          "restriction": "allow", 
          "begin": "2019-08-23", 
          "end": "2019-08-23", 
          "notes": [
            {
              "source": "wikidata", 
              "type": "extension", 
              "subnotes": [
                {
                  "content": [
                    "sint incididunt eiusmod ex aute aliquip", 
                    "duis consectetur ad commodo fugiat in", 
                    "Lorem culpa fugiat tempor enim aliquip"
                  ], 
                  "type": "text"
                }
              ], 
              "title": "tempor ea consectetur"
            }
          ], 
          "act": "disseminate"
        }, 
        {
          "restriction": "disallow", 
          "begin": "2019-08-23", 
          "end": "2019-08-23", 
          "notes": [], 
          "act": "use"
        }
      ], 
      "rights_status": "unknown", 
      "determination_date": "2019-08-23", 
      "type": "rights_statement", 
      "id": "5d604ab8579f53ac339b2673", 
      "rights_type": "copyright"
    }
  ], 
  "agents": [
    {
      "ref": "/agents_software/774", 
      "type": "software"
    }, 
    {
      "ref": "/agents_person/309", 
      "type": "person"
    }, 
    {
      "ref": "/agents_family/805", 
      "type": "family"
    }, 
    {
      "ref": "/agents_family/7", 
      "type": "family"
    }, 
    {
      "ref": "/agents_person/183", 
      "type": "person"
    }
  ], 
  "terms": [
    {
      "ref": "/terms/322"
    }, 
    {
      "ref": "/terms/149"
    }, 
    {
      "ref": "/terms/884"
    }, 
    {
      "ref": "/terms/362"
    }, 
    {
      "ref": "/terms/818"
    }
  ], 
  "type": "object", 
  "id": "5d604ab8958cdc637c3e340e"
}