{
  "index": 35,
  "id": "5d71577c8394bc18d1190bd2",
  "title": "Fugiat irure officia velit veniam amet ut eu et esse sint tempor.",
  "type": "collection",
  "level": "otherLevel",
  "dates": [
    {
      "begin": "1943-03-29",
      "end": "1986-02-13",
      "expression": "Mar 29th, 1943 - Feb 13th, 1986",
      "type": "inclusive",
      "label": "copyright"
    }
  ],
  "creators": [
    {
      "external_identifiers": [
        {
          "source": "archivesspace",
          "identifier": "/agents_person/2"
        }
      ]
    }
  ],
  "extents": [
    {
      "value": "6.75",
      "type": "files"
    }
  ],
  "notes": [
    {
      "type": "physdesc",
      "title": "irure eiusmod amet",
      "source": "archivesspace",
      "subnotes": [
        {
          "type": "orderedlist",
          "content": [
            "dolor dolore culpa in voluptate irure",
            "quis amet non non ipsum pariatur",
            "mollit nisi ullamco ullamco labore mollit"
          ]
        },
        {
          "type": "definedlist",
          "content": [
            "amet nisi dolor nostrud nulla ullamco",
            "sunt adipisicing ipsum aliquip consequat ut",
            "commodo eiusmod ut reprehenderit irure laboris"
          ]
        },
        {
          "type": "orderedlist",
          "content": [
            "dolor nostrud aliqua dolore et proident",
            "minim ea nisi aliquip commodo fugiat"
          ]
        }
      ]
    }
  ],
  "terms": [
    {
      "external_identifiers": [
        {
          "source": "archivesspace",
          "identifier": "/terms/5"
        }
      ]
    },
    {
      "external_identifiers": [
        {
          "source": "archivesspace",
          "identifier": "/terms/16"
        }
      ]
    },
    {
      "external_identifiers": [
        {
          "source": "archivesspace",
          "identifier": "/terms/43"
        }
      ]
    }
  ],
  "agents": [
    {
      "external_identifiers": [
        {
          "source": "archivesspace",
          "identifier": "/agents_family/42"
        }
      ]
    },
    {
      "external_identifiers": [
        {
          "source": "archivesspace",
          "identifier": "/agents_organization/42"
        }
      ]
    },
    {
      "external_identifiers": [
        {
          "source": "archivesspace",
          "identifier": "/agents_person/41"
        }
      ]
    },
    {
      "external_identifiers": [
        {
          "source": "archivesspace",
          "identifier": "/agents_person/6"
        }
      ]
    },
    {
      "external_identifiers": [
        {
          "source": "archivesspace",
          "identifier": "/agents_person/5"
        }
      ]
    }
  ],
  "languages": [
    {
      "expression": "Spanish",
      "identifier": "spa"
    },
    {
      "expression": "Esperanto",
      "identifier": "epo"
    },
    {
      "expression": "English",
      "identifier": "eng"
    }
  ],
  "rights_statements": [],
  "ancestors": [
    {
      "external_identifiers": [
        {
          "source": "archivesspace",
          "identifier": "/repositories/2/archival_objects/18"
        }
      ]
    },
    {
      "external_identifiers": [
        {
          "source": "archivesspace",
          "identifier": "/repositories/2/archival_objects/33"
        }
      ]
    }
  ],
  "children": [
    {
      "external_identifiers": [
        {
          "source": "archivesspace",
          "identifier": "/repositories/2/archival_objects/31"
        }
      ]
    },
    {
      "external_identifiers": [
        {
          "source": "archivesspace",
          "identifier": "/repositories/2/archival_objects/16"
        }
      ]
    }
  ],
  "external_identifiers": [
    {
      "source": "archivesspace",
      "identifier": "/repositories/2/archival_objects/35"
    }
  ]
}